{
  "base": "GBP", 
  "period": {
    "end": "2018-12-31", 
    "start": "2018-12-01"
  }, 
  "rates": {
    "AED": "4.6934", 
    "ALL": "139.53", 
    "AMD": "618.82", 
    "AOA": "396.62", 
    "ARS": "46.32", 
    "AUD": "1.7594", 
    "AWG": "2.2872", 
    "AZN": "2.1678", 
    "BAM": "2.1934", 
    "BBD": "2.5556", 
    "BDT": "107.17", 
    "BGN": "2.1933", 
    "BHD": "0.4817", 
    "BIF": "2296.56", 
    "BMD": "1.2778", 
    "BND": "1.7537", 
    "BOB": "8.8295", 
    "BRL": "4.8461", 
    "BSD": "1.2778", 
    "BTN": "91.34", 
    "BWP": "13.5", 
    "BYN": "2.6904", 
    "BZD": "2.554", 
    "CAD": "1.6988", 
    "CDF": "2071.3", 
    "CHF": "1.272", 
    "CLP": "885.34", 
    "CNY": "8.8669", 
    "COP": "4091.47", 
    "CRC": "766.92", 
    "CUP": "1.2778", 
    "CVE": "124.09", 
    "CZK": "29.16", 
    "DJF": "227.08", 
    "DKK": "8.3679", 
    "DOP": "63.72", 
    "DZD": "151.54", 
    "ECS": "1.2778", 
    "EGP": "22.94", 
    "ERN": "19.16", 
    "ETB": "35.6", 
    "EUR": "1.1215", 
    "FJD": "2.7041", 
    "GEL": "3.3925", 
    "GHS": "6.1845", 
    "GMD": "63.26", 
    "GNF": "11604.28", 
    "GTQ": "9.8317", 
    "GYD": "266.57", 
    "HKD": "10", 
    "HNL": "31", 
    "HRK": "8.3346", 
    "HTG": "93.9", 
    "HUF": "360.72", 
    "IDR": "18662.18", 
    "ILS": "4.7651", 
    "INR": "91.34", 
    "IQD": "1520.57", 
    "ISK": "158.35", 
    "JMD": "160.76", 
    "JOD": "0.907", 
    "JPY": "144.35", 
    "KES": "130.71", 
    "KGS": "89.22", 
    "KHR": "5163.55", 
    "KMF": "551.72", 
    "KRW": "1446.07", 
    "KWD": "0.3886", 
    "KYD": "1.0478", 
    "KZT": "470.63", 
    "LAK": "10918.73", 
    "LBP": "1933.29", 
    "LKR": "228.39", 
    "LRD": "1.2778", 
    "LSL": "17.77", 
    "LYD": "1.7953", 
    "MAD": "12.12", 
    "MDL": "21.89", 
    "MGA": "4657.55", 
    "MKD": "68.94", 
    "MMK": "2041.14", 
    "MNT": "3296.7", 
    "MOP": "10.3", 
    "MRO": "456.55", 
    "MUR": "43.95", 
    "MVR": "19.75", 
    "MWK": "931.64", 
    "MXN": "25.83", 
    "MYR": "5.3597", 
    "MZN": "78.48", 
    "NGN": "464.47", 
    "NIO": "41.09", 
    "NOK": "10.91", 
    "NPR": "146.14", 
    "NZD": "1.8676", 
    "OMR": "0.4919", 
    "PAB": "1.2778", 
    "PEN": "4.315", 
    "PGK": "4.3051", 
    "PHP": "66.9", 
    "PKR": "171.19", 
    "PLN": "4.8262", 
    "PYG": "7574.58", 
    "QAR": "4.6528", 
    "RON": "5.2298", 
    "RSD": "132.75", 
    "RUB": "84.16", 
    "RWF": "1136.6", 
    "SAR": "4.7943", 
    "SBD": "10.23", 
    "SCR": "17.74", 
    "SDG": "60.84", 
    "SEK": "11.56", 
    "SGD": "1.7537", 
    "SLL": "10637.61", 
    "SOS": "742.39", 
    "SRD": "9.5298", 
    "STD": "27568.4", 
    "SVC": "11.18", 
    "SZL": "17.77", 
    "THB": "42.13", 
    "TMT": "4.4723", 
    "TND": "3.7235", 
    "TOP": "1.7594", 
    "TRY": "6.792", 
    "TTD": "8.623", 
    "TWD": "39.46", 
    "TZS": "2952.97", 
    "UAH": "35.42", 
    "UGX": "4753.38", 
    "USD": "1.2778", 
    "UYU": "41.53", 
    "UZS": "10576.96", 
    "VEF": "317617.87", 
    "VND": "29840.32", 
    "VUV": "144.26", 
    "WST": "3.3001", 
    "XAF": "735.62", 
    "XCD": "3.45", 
    "XOF": "735.62", 
    "XPF": "133.82", 
    "YER": "319.61", 
    "ZAR": "17.77", 
    "ZMW": "15.23", 
    "ZWL": "462.43"
  }
}
