{
  "base": "GBP",
  "period": {
    "end": "2024-03-31",
    "start": "2024-03-01"
  },
  "rates": {
    "AED": "4.6327",
    "ALL": "121.1471",
    "AMD": "509.9746",
    "AOA": "1054.5481",
    "ARS": "1056.2063",
    "AUD": "1.9252",
    "AWG": "2.2580",
    "AZN": "2.1464",
    "BAM": "2.2848",
    "BBD": "2.5229",
    "BDT": "138.3268",
    "BGN": "2.2848",
    "BHD": "0.4743",
    "BIF": "3600.6163",
    "BMD": "1.2614",
    "BND": "1.6959",
    "BOB": "8.7123",
    "BRL": "6.2167",
    "BSD": "1.2614",
    "BTN": "104.6369",
    "BWP": "17.2573",
    "BYN": "4.1259",
    "BZD": "2.5413",
    "CAD": "1.7064",
    "CDF": "3494.2655",
    "CHF": "1.1104",
    "CLP": "1215.9271",
    "CNY": "9.0701",
    "COP": "4949.0201",
    "CRC": "648.6513",
    "CUP": "30.2386",
    "CVE": "128.8160",
    "CZK": "29.6576",
    "DJF": "224.4970",
    "DKK": "8.7079",
    "DOP": "73.8621",
    "DZD": "169.7528",
    "EGP": "39.0307",
    "ERN": "18.9217",
    "ETB": "71.4589",
    "EUR": "1.1682",
    "FJD": "2.8535",
    "GEL": "3.3424",
    "GHS": "15.7833",
    "GMD": "85.4233",
    "GNF": "10808.7720",
    "GTQ": "9.8375",
    "GYD": "263.4359",
    "HKD": "9.8667",
    "HNL": "31.1011",
    "HTG": "167.1876",
    "HUF": "453.1681",
    "IDR": "19726.1100",
    "ILS": "4.6410",
    "INR": "104.6369",
    "IQD": "1650.4353",
    "ISK": "173.2519",
    "JMD": "197.3766",
    "JOD": "0.8944",
    "JPY": "189.3119",
    "KES": "183.5712",
    "KGS": "112.8099",
    "KHR": "5137.2178",
    "KMF": "574.7104",
    "KRW": "1683.5372",
    "KWD": "0.3882",
    "KYD": "1.0369",
    "KZT": "568.3821",
    "LAK": "26236.5767",
    "LBP": "18921.2352",
    "LKR": "392.7616",
    "LRD": "241.2722",
    "LSL": "23.8639",
    "LYD": "6.1007",
    "MAD": "12.7248",
    "MDL": "22.5596",
    "MGA": "5725.0752",
    "MKD": "71.9857",
    "MMK": "2646.0834",
    "MNT": "4293.1324",
    "MOP": "10.1627",
    "MRU": "50.0616",
    "MUR": "58.0333",
    "MVR": "19.4400",
    "MWK": "2120.9393",
    "MXN": "21.5151",
    "MYR": "6.0475",
    "MZN": "80.5497",
    "NGN": "2011.5792",
    "NIO": "46.3527",
    "NOK": "13.2278",
    "NPR": "167.4975",
    "NZD": "2.0402",
    "OMR": "0.4857",
    "PAB": "1.2614",
    "PEN": "4.7731",
    "PGK": "4.7509",
    "PHP": "70.5776",
    "PKR": "352.6072",
    "PLN": "5.0385",
    "PYG": "9201.8160",
    "QAR": "4.5917",
    "RON": "5.8133",
    "RSD": "136.9006",
    "RUB": "116.3131",
    "RWF": "1605.8100",
    "SAR": "4.7304",
    "SBD": "10.4853",
    "SCR": "17.3801",
    "SDG": "757.7077",
    "SEK": "13.0950",
    "SGD": "1.6959",
    "SLE": "28.7501",
    "SOS": "720.6312",
    "SRD": "44.8169",
    "SVC": "11.0377",
    "SZL": "23.8639",
    "THB": "45.2204",
    "TMT": "4.4107",
    "TND": "3.9410",
    "TOP": "2.9693",
    "TRY": "39.0863",
    "TTD": "8.5533",
    "TWD": "39.7699",
    "TZS": "3202.3171",
    "UAH": "48.7065",
    "UGX": "4904.8204",
    "USD": "1.2614",
    "UYU": "49.3034",
    "UZS": "15728.3897",
    "VEF": "4570650.1346",
    "VND": "30825.7980",
    "VUV": "151.4872",
    "WST": "3.4571",
    "XAF": "766.2805",
    "XCD": "3.4088",
    "XOF": "766.2805",
    "XPF": "139.4018",
    "YER": "315.7542",
    "ZAR": "23.8639",
    "ZMW": "28.7430",
    "ZWL": "16576.6675"
  }
}